llm_json_adapter/__init__.py
llm_json_adapter/exceptions.py
llm_json_adapter/llm_json_adapter.py
llm_json_adapter/objects/__init__.py
llm_json_adapter/objects/response.py
llm_json_adapter/providers/__init__.py
llm_json_adapter/providers/bedrock/__init__.py
llm_json_adapter/providers/bedrock/provider.py
llm_json_adapter/providers/google/__init__.py
llm_json_adapter/providers/google/provider.py
llm_json_adapter/providers/languages.py
llm_json_adapter/providers/ollama/__init__.py
llm_json_adapter/providers/ollama/provider.py
llm_json_adapter/providers/openai/__init__.py
llm_json_adapter/providers/openai/provider.py
llm_json_adapter/providers/provider.py
llm_json_adapter/schemas/2020-12.schema.json
llm_json_adapter/utilities/__init__.py
llm_json_adapter/utilities/json_utility.py
llm_json_adapter-0.2.0.dist-info/LICENSE
llm_json_adapter-0.2.0.dist-info/METADATA
llm_json_adapter-0.2.0.dist-info/WHEEL
llm_json_adapter-0.2.0.dist-info/RECORD
