Metadata-Version: 2.1
Name: llm-json-adapter
Version: 0.2.0
Summary: 
Author: Takaaki Mizuno
Requires-Python: >=3.10,<4.0
Classifier: Programming Language :: Python :: 3
Classifier: Programming Language :: Python :: 3.10
Classifier: Programming Language :: Python :: 3.11
Classifier: Programming Language :: Python :: 3.12
Requires-Dist: jsonschema (>=4.20.0,<5.0.0)
Requires-Dist: pydantic (>=2.5.3,<3.0.0)
